htpbs/__init__.py
htpbs/bar.py
htpbs/progressbars.py
htpbs-0.0.4.dist-info/LICENSE.txt
htpbs-0.0.4.dist-info/METADATA
htpbs-0.0.4.dist-info/WHEEL
htpbs-0.0.4.dist-info/top_level.txt
htpbs-0.0.4.dist-info/RECORD
