Metadata-Version: 2.1
Name: htpbs
Version: 0.0.4
Summary: A Python module that creates horizontal progress bars to keep track of the progress of threaded jobs. Progress Bars in this module are totally customizable
Home-page: https://github.com/jortizcostadev/htpbs
Author: Jose Ortiz
Author-email: csjortizco@gmail.com
License: MIT
Download-URL: https://pypi.org/project/htpbs/
Keywords: Bars,Horizontal,Progress Bars,Threaded
Platform: UNKNOWN
Requires-Python: >=3.6
